mylib/__init__.py
ipa_sdk-0.0.1.dist-info/METADATA
ipa_sdk-0.0.1.dist-info/WHEEL
ipa_sdk-0.0.1.dist-info/top_level.txt
ipa_sdk-0.0.1.dist-info/RECORD
