Metadata-Version: 2.4
Name: ipa-sdk
Version: 0.0.1
Summary: template python project with necessary configurations
Author-email: xdewx <present150608@sina.com>
Requires-Python: >=3.10
